Workbook

Sheet BOM
A1: No | B1: Item (exact model) | C1: Qty | D1: Unit price (INR) | E1: Line total (INR) | F1: Supplier | G1: Product / search URL | H1: Notes
A2: 1 | B2: ESP32 DevKit V1 (ESP32-WROOM-32, 30-pin, CP2102) | C2: 2 | D2: 499 | E2: =C2*D2 -> 998 | F2: Probots | G2: https://probots.co.in/esp32-30-pin-cp2102-development-board.html | H2: Controller. 1 spare: GPIO damage is the most common failure. Listed at Rs 499 incl. GST.
A3: 2 | B3: TCRT5000 Reflective IR Sensor Photoelectric Switch Pack of 5 | C3: 2 | D3: Rs 69.00 | E3: Rs 138.00 | F3: Robu.in | G3: https://robu.in/product/tcrt5000-reflective-ir-sensor-photoelectric-switch/ | H3: 5 for array + 3 spare. Use AO (analog), run from 3.3 V. Price not shown in search snippet; confirm on page.
A4: 3 | B4: N20 12 V 300 RPM micro metal gear motor WITH encoder | C4: 1 | D4: 514.48 | E4: =C4*D4 -> 514.48 | F4: Zbotic | G4: https://zbotic.in/product/n20-12v-300rpm-micro-metal-gear-motor-with-encoder/ | H4: Upgrade over the plain motor: encoders give speed feedback. Rs 436 + GST.
A5: 4 | B5: N20 motor bracket (pair-compatible) | C5: 5 | D5: Rs 27.80 | E5: Rs 139.00 | F5: Amazon | G5: https://www.amazon.in/Motor-Mount-Bracket-N20-2pcs/dp/B094ZJVZ1L | H5: 2 in use + 2 spare. Search link: pick the bracket sold for N20.
A6: 5 | B6: 43 mm rubber-tyre wheel for N20 (3 mm D-shaft) | C6: 2 | D6: Rs 38.00 | E6: Rs 76.00 | F6: Robu.in | G6: https://robu.in/?s=43mm+wheel+N20&post_type=product | H6: ~0.52 m/s no-load at ~9.3 V.
A7: 6 | B7: Metal ball caster 3/8 in | C7: 2 | D7: 80 | E7: =C7*D7 -> 160 | F7: Probots | G7: https://probots.co.in/catalogsearch/result/?q=metal+ball+caster | H7: Low-friction 3rd contact point; 1 spare.
A8: 7 | B8: L298N dual H-bridge motor driver module | C8: 2 | D8: 149 | E8: =C8*D8 -> 298 | F8: Probots | G8: https://probots.co.in/l298n-2a-dual-motor-driver-module.html | H8: Matches Appendix A pin map. 1 spare (easy to burn during bring-up). Rs 149 incl. GST.
A9: 8 | B9: CNHL MiniStar 3S 11.1 V 1000 mAh 100C LiPo, XT60 | C9: 2 | D9: 1066.72 | E9: =C9*D9 -> 2133.44 | F9: Zbotic | G9: https://zbotic.in/product/cnhl-ministar-1000mah-11-1v-3s-100c-lipo-battery-with-xt60-plug/ | H9: Two packs: run one while the other charges. Rs 904 + GST each, free shipping stated.
A10: 9 | B10: IMAX RC B3 Pro balance charger 2S/3S (EU plug) | C10: 1 | D10: 499 | E10: =C10*D10 -> 499 | F10: Probots | G10: https://probots.co.in/imax-b3-pro-balance-charger-for-2s-3s-lipo-battery.html | H10: Mandatory for safe LiPo charging. Rs 499 incl. GST.
A11: 10 | B11: LiPo low-voltage buzzer alarm (1-8S) | C11: 2 | D11: 150 | E11: =C11*D11 -> 300 | F11: Robu.in | G11: https://robu.in/?s=lipo+low+voltage+buzzer+alarm&post_type=product | H11: One per pack. Stops over-discharge below ~3.3 V/cell.
A12: 11 | B12: XT60 connector pair (robot side) | C12: 2 | D12: 60 | E12: =C12*D12 -> 120 | F12: Probots | G12: https://probots.co.in/catalogsearch/result/?q=XT60+connector | H12: Robot-side battery connector; 1 spare.
A13: 12 | B13: Rocker switch 6 A | C13: 2 | D13: 35 | E13: =C13*D13 -> 70 | F13: Robu.in | G13: https://robu.in/?s=rocker+switch+6A&post_type=product | H13: Main power switch.
A14: 13 | B14: Blade fuse holder + 5 A fuse | C14: 2 | D14: 80 | E14: =C14*D14 -> 160 | F14: Robu.in | G14: https://robu.in/?s=blade+fuse+holder&post_type=product | H14: Short-circuit protection (worst case 1.9 A).
A15: 14 | B15: MP1584EN buck module (set to 5.0 V) | C15: 2 | D15: 79 | E15: =C15*D15 -> 158 | F15: Probots | G15: https://probots.co.in/mp1584-dc-dc-step-down-3a-adjustable-buck-module.html | H15: 5 V rail for ESP32 Vin + L298N logic. 1 spare: the trimpot is fragile. Rs 79 incl. GST.
A16: 15 | B16: 3 mm acrylic chassis plate, laser cut (or 3D-print) | C16: 1 | D16: 450 | E16: =C16*D16 -> 450 | F16: Local fabricator | G16: https://robu.in/?s=robot+chassis+acrylic&post_type=product | H16: Custom 2-deck chassis; local laser-cut price is a guess. Search link is only a fallback.
A17: 16 | B17: M3 standoff + screw kit | C17: 1 | D17: 200 | E17: =C17*D17 -> 200 | F17: Probots | G17: https://probots.co.in/catalogsearch/result/?q=M3+standoff+screw+kit | H17: Mounting decks.
A18: 17 | B18: Perfboard 5x7 cm | C18: 4 | D18: 30 | E18: =C18*D18 -> 120 | F18: Probots | G18: https://probots.co.in/catalogsearch/result/?q=perfboard+5x7 | H18: Sensor-array / power distribution boards.
... A27: 26 | B27: LiPo safe charging bag | C27: 1 | D27: 250 | E27: =C27*D27 -> 250 | F27: Robu.in | G27: https://robu.in/?s=lipo+safe+bag&post_type=product | H27: Fire-resistant bag for charging/storage.

Sheet Summary
A1: LMS Line-Following Robot: Budget Summary
A3: Maximum budget | B3: 10000
A4: Parts subtotal | B4: =SUM(BOM!E2:E27) -> 7680.92
A5: Shipping (assumed, 3 orders) | B5: 400
A6: Committed spend | B6: =B4+B5 -> 8080.92
A7: Reserve / contingency (budget left) | B7: =MAX(0,B3-B6) -> 1919.08
A8: TOTAL (committed + reserve) | B8: =B6+B7 -> 10000
A9: Reserve as % of budget | B9: =B7/B3 -> 0.191908
A10: Status | B10: =IF(B6<=B3,"Within budget","OVER BUDGET") -> Within budget
A12: Spend by supplier (parts only)
A13: Probots | B13: =SUMIF(BOM!F2:F27,A13,BOM!E2:E27) -> 2773
A14: Zbotic | B14: =SUMIF(BOM!F2:F27,A14,BOM!E2:E27) -> 2647.92
A15: Robu.in | B15: =SUMIF(BOM!F2:F27,A15,BOM!E2:E27) -> 1810
A16: Local fabricator | B16: =SUMIF(BOM!F2:F27,A16,BOM!E2:E27) -> 450
A18: Share of parts cost with a verified listing price | B18: =SUMIF(BOM!#REF!,"Verified listing",BOM!E2:E27)/B4 -> #REF!
A20: Legend
A21: Blue numbers = inputs you can change (budget, shipping, qty, unit price).
A22: Green 'Price basis' = price read from a live shop listing. Yellow = my estimate: check it before ordering.
A23: Black = formulas; everything recalculates when you edit qty or price.

Sheet Notes
A1: Sources and assumptions
A2: Verified prices came from product pages found by web search while preparing this sheet (late Oct 2026). Shop prices change daily: re-check each before paying.
A3: Verified items: ESP32 (Probots), L298N (Probots), IMAX B3 Pro charger (Probots), MP1584 buck (Probots), CNHL MiniStar 3S LiPo (Zbotic), N20 12V 300RPM encoder motor (Zbotic).
A4: Estimated items: I could not confirm a live price for the rest. Their URLs are store search links, not individual product pages. Open the link, pick the matching part, and update the blue unit price.
A5: The N20 encoder motor page was marked out of stock on a Zbotic category listing: confirm before ordering. The encoder pins are not used by the current firmware; they are for future speed feedback.
A6: Shipping of Rs 400 is an assumption for 3 supplier orders; Zbotic states free shipping on orders above Rs 999.
A7: Changes from the original BOM: 2 batteries, spare ESP32 / L298N / buck / sensors, encoder motors, multimeter and LiPo bag added to use the full Rs 10,000 budget safely.
A8: Safety: charge LiPo only with the balance charger, in the safe bag, and never unattended. Set the buck to 5.0 V with the multimeter before connecting the ESP32.
